coordml_cli/__init__.py
coordml_cli/cli.py
coordml_cli/client.py
coordml_cli/exp_config.py
coordml_cli-0.0.2.dist-info/LICENSE
coordml_cli-0.0.2.dist-info/METADATA
coordml_cli-0.0.2.dist-info/WHEEL
coordml_cli-0.0.2.dist-info/entry_points.txt
coordml_cli-0.0.2.dist-info/top_level.txt
coordml_cli-0.0.2.dist-info/RECORD
