Metadata-Version: 2.1
Name: coordml-cli
Version: 0.0.2
Summary: CLI for CoordML Central
Home-page: https://github.com/coordml/cli
Author: Yichen Xu
Author-email: yichen.xu@monad.email
License: UNKNOWN
Platform: UNKNOWN
Classifier: Programming Language :: Python :: 3
Classifier: License :: OSI Approved :: MIT License
Classifier: Operating System :: OS Independent
Requires-Python: >=3.7
Requires-Dist: requests
Requires-Dist: pyyaml
